[{"tag":{"S":"Al6101CAwh_NKR-gr67Xx/_N_T_/layout"},"path":{"S":"Al6101CAwh_NKR-gr67Xx/apple-icon.jpg"},"revalidatedAt":{"N":"1"}},{"tag":{"S":"Al6101CAwh_NKR-gr67Xx/_N_T_/apple-icon.jpg/layout"},"path":{"S":"Al6101CAwh_NKR-gr67Xx/apple-icon.jpg"},"revalidatedAt":{"N":"1"}},{"tag":{"S":"Al6101CAwh_NKR-gr67Xx/_N_T_/apple-icon.jpg/route"},"path":{"S":"Al6101CAwh_NKR-gr67Xx/apple-icon.jpg"},"revalidatedAt":{"N":"1"}},{"tag":{"S":"Al6101CAwh_NKR-gr67Xx/_N_T_/apple-icon.jpg"},"path":{"S":"Al6101CAwh_NKR-gr67Xx/apple-icon.jpg"},"revalidatedAt":{"N":"1"}},{"tag":{"S":"Al6101CAwh_NKR-gr67Xx/_N_T_/layout"},"path":{"S":"Al6101CAwh_NKR-gr67Xx/carrinho"},"revalidatedAt":{"N":"1"}},{"tag":{"S":"Al6101CAwh_NKR-gr67Xx/_N_T_/(storefront)/layout"},"path":{"S":"Al6101CAwh_NKR-gr67Xx/carrinho"},"revalidatedAt":{"N":"1"}},{"tag":{"S":"Al6101CAwh_NKR-gr67Xx/_N_T_/(storefront)/carrinho/layout"},"path":{"S":"Al6101CAwh_NKR-gr67Xx/carrinho"},"revalidatedAt":{"N":"1"}},{"tag":{"S":"Al6101CAwh_NKR-gr67Xx/_N_T_/(storefront)/carrinho/page"},"path":{"S":"Al6101CAwh_NKR-gr67Xx/carrinho"},"revalidatedAt":{"N":"1"}},{"tag":{"S":"Al6101CAwh_NKR-gr67Xx/_N_T_/carrinho"},"path":{"S":"Al6101CAwh_NKR-gr67Xx/carrinho"},"revalidatedAt":{"N":"1"}},{"tag":{"S":"Al6101CAwh_NKR-gr67Xx/_N_T_/layout"},"path":{"S":"Al6101CAwh_NKR-gr67Xx/categorias"},"revalidatedAt":{"N":"1"}},{"tag":{"S":"Al6101CAwh_NKR-gr67Xx/_N_T_/(storefront)/layout"},"path":{"S":"Al6101CAwh_NKR-gr67Xx/categorias"},"revalidatedAt":{"N":"1"}},{"tag":{"S":"Al6101CAwh_NKR-gr67Xx/_N_T_/(storefront)/categorias/layout"},"path":{"S":"Al6101CAwh_NKR-gr67Xx/categorias"},"revalidatedAt":{"N":"1"}},{"tag":{"S":"Al6101CAwh_NKR-gr67Xx/_N_T_/(storefront)/categorias/page"},"path":{"S":"Al6101CAwh_NKR-gr67Xx/categorias"},"revalidatedAt":{"N":"1"}},{"tag":{"S":"Al6101CAwh_NKR-gr67Xx/_N_T_/categorias"},"path":{"S":"Al6101CAwh_NKR-gr67Xx/categorias"},"revalidatedAt":{"N":"1"}},{"tag":{"S":"Al6101CAwh_NKR-gr67Xx/_N_T_/layout"},"path":{"S":"Al6101CAwh_NKR-gr67Xx/conta\\cadastro"},"revalidatedAt":{"N":"1"}},{"tag":{"S":"Al6101CAwh_NKR-gr67Xx/_N_T_/(storefront)/layout"},"path":{"S":"Al6101CAwh_NKR-gr67Xx/conta\\cadastro"},"revalidatedAt":{"N":"1"}},{"tag":{"S":"Al6101CAwh_NKR-gr67Xx/_N_T_/(storefront)/conta/layout"},"path":{"S":"Al6101CAwh_NKR-gr67Xx/conta\\cadastro"},"revalidatedAt":{"N":"1"}},{"tag":{"S":"Al6101CAwh_NKR-gr67Xx/_N_T_/(storefront)/conta/cadastro/layout"},"path":{"S":"Al6101CAwh_NKR-gr67Xx/conta\\cadastro"},"revalidatedAt":{"N":"1"}},{"tag":{"S":"Al6101CAwh_NKR-gr67Xx/_N_T_/(storefront)/conta/cadastro/page"},"path":{"S":"Al6101CAwh_NKR-gr67Xx/conta\\cadastro"},"revalidatedAt":{"N":"1"}},{"tag":{"S":"Al6101CAwh_NKR-gr67Xx/_N_T_/conta/cadastro"},"path":{"S":"Al6101CAwh_NKR-gr67Xx/conta\\cadastro"},"revalidatedAt":{"N":"1"}},{"tag":{"S":"Al6101CAwh_NKR-gr67Xx/_N_T_/layout"},"path":{"S":"Al6101CAwh_NKR-gr67Xx/conta\\login"},"revalidatedAt":{"N":"1"}},{"tag":{"S":"Al6101CAwh_NKR-gr67Xx/_N_T_/(storefront)/layout"},"path":{"S":"Al6101CAwh_NKR-gr67Xx/conta\\login"},"revalidatedAt":{"N":"1"}},{"tag":{"S":"Al6101CAwh_NKR-gr67Xx/_N_T_/(storefront)/conta/layout"},"path":{"S":"Al6101CAwh_NKR-gr67Xx/conta\\login"},"revalidatedAt":{"N":"1"}},{"tag":{"S":"Al6101CAwh_NKR-gr67Xx/_N_T_/(storefront)/conta/login/layout"},"path":{"S":"Al6101CAwh_NKR-gr67Xx/conta\\login"},"revalidatedAt":{"N":"1"}},{"tag":{"S":"Al6101CAwh_NKR-gr67Xx/_N_T_/(storefront)/conta/login/page"},"path":{"S":"Al6101CAwh_NKR-gr67Xx/conta\\login"},"revalidatedAt":{"N":"1"}},{"tag":{"S":"Al6101CAwh_NKR-gr67Xx/_N_T_/conta/login"},"path":{"S":"Al6101CAwh_NKR-gr67Xx/conta\\login"},"revalidatedAt":{"N":"1"}},{"tag":{"S":"Al6101CAwh_NKR-gr67Xx/_N_T_/layout"},"path":{"S":"Al6101CAwh_NKR-gr67Xx/contato"},"revalidatedAt":{"N":"1"}},{"tag":{"S":"Al6101CAwh_NKR-gr67Xx/_N_T_/(storefront)/layout"},"path":{"S":"Al6101CAwh_NKR-gr67Xx/contato"},"revalidatedAt":{"N":"1"}},{"tag":{"S":"Al6101CAwh_NKR-gr67Xx/_N_T_/(storefront)/contato/layout"},"path":{"S":"Al6101CAwh_NKR-gr67Xx/contato"},"revalidatedAt":{"N":"1"}},{"tag":{"S":"Al6101CAwh_NKR-gr67Xx/_N_T_/(storefront)/contato/page"},"path":{"S":"Al6101CAwh_NKR-gr67Xx/contato"},"revalidatedAt":{"N":"1"}},{"tag":{"S":"Al6101CAwh_NKR-gr67Xx/_N_T_/contato"},"path":{"S":"Al6101CAwh_NKR-gr67Xx/contato"},"revalidatedAt":{"N":"1"}},{"tag":{"S":"Al6101CAwh_NKR-gr67Xx/_N_T_/layout"},"path":{"S":"Al6101CAwh_NKR-gr67Xx/icon.jpg"},"revalidatedAt":{"N":"1"}},{"tag":{"S":"Al6101CAwh_NKR-gr67Xx/_N_T_/icon.jpg/layout"},"path":{"S":"Al6101CAwh_NKR-gr67Xx/icon.jpg"},"revalidatedAt":{"N":"1"}},{"tag":{"S":"Al6101CAwh_NKR-gr67Xx/_N_T_/icon.jpg/route"},"path":{"S":"Al6101CAwh_NKR-gr67Xx/icon.jpg"},"revalidatedAt":{"N":"1"}},{"tag":{"S":"Al6101CAwh_NKR-gr67Xx/_N_T_/icon.jpg"},"path":{"S":"Al6101CAwh_NKR-gr67Xx/icon.jpg"},"revalidatedAt":{"N":"1"}},{"tag":{"S":"Al6101CAwh_NKR-gr67Xx/_N_T_/layout"},"path":{"S":"Al6101CAwh_NKR-gr67Xx/index"},"revalidatedAt":{"N":"1"}},{"tag":{"S":"Al6101CAwh_NKR-gr67Xx/_N_T_/(storefront)/layout"},"path":{"S":"Al6101CAwh_NKR-gr67Xx/index"},"revalidatedAt":{"N":"1"}},{"tag":{"S":"Al6101CAwh_NKR-gr67Xx/_N_T_/(storefront)/page"},"path":{"S":"Al6101CAwh_NKR-gr67Xx/index"},"revalidatedAt":{"N":"1"}},{"tag":{"S":"Al6101CAwh_NKR-gr67Xx/_N_T_/"},"path":{"S":"Al6101CAwh_NKR-gr67Xx/index"},"revalidatedAt":{"N":"1"}},{"tag":{"S":"Al6101CAwh_NKR-gr67Xx/_N_T_/index"},"path":{"S":"Al6101CAwh_NKR-gr67Xx/index"},"revalidatedAt":{"N":"1"}},{"tag":{"S":"Al6101CAwh_NKR-gr67Xx/_N_T_/layout"},"path":{"S":"Al6101CAwh_NKR-gr67Xx/sobre"},"revalidatedAt":{"N":"1"}},{"tag":{"S":"Al6101CAwh_NKR-gr67Xx/_N_T_/(storefront)/layout"},"path":{"S":"Al6101CAwh_NKR-gr67Xx/sobre"},"revalidatedAt":{"N":"1"}},{"tag":{"S":"Al6101CAwh_NKR-gr67Xx/_N_T_/(storefront)/sobre/layout"},"path":{"S":"Al6101CAwh_NKR-gr67Xx/sobre"},"revalidatedAt":{"N":"1"}},{"tag":{"S":"Al6101CAwh_NKR-gr67Xx/_N_T_/(storefront)/sobre/page"},"path":{"S":"Al6101CAwh_NKR-gr67Xx/sobre"},"revalidatedAt":{"N":"1"}},{"tag":{"S":"Al6101CAwh_NKR-gr67Xx/_N_T_/sobre"},"path":{"S":"Al6101CAwh_NKR-gr67Xx/sobre"},"revalidatedAt":{"N":"1"}},{"tag":{"S":"Al6101CAwh_NKR-gr67Xx/_N_T_/layout"},"path":{"S":"Al6101CAwh_NKR-gr67Xx/termos"},"revalidatedAt":{"N":"1"}},{"tag":{"S":"Al6101CAwh_NKR-gr67Xx/_N_T_/(storefront)/layout"},"path":{"S":"Al6101CAwh_NKR-gr67Xx/termos"},"revalidatedAt":{"N":"1"}},{"tag":{"S":"Al6101CAwh_NKR-gr67Xx/_N_T_/(storefront)/termos/layout"},"path":{"S":"Al6101CAwh_NKR-gr67Xx/termos"},"revalidatedAt":{"N":"1"}},{"tag":{"S":"Al6101CAwh_NKR-gr67Xx/_N_T_/(storefront)/termos/page"},"path":{"S":"Al6101CAwh_NKR-gr67Xx/termos"},"revalidatedAt":{"N":"1"}},{"tag":{"S":"Al6101CAwh_NKR-gr67Xx/_N_T_/termos"},"path":{"S":"Al6101CAwh_NKR-gr67Xx/termos"},"revalidatedAt":{"N":"1"}},{"tag":{"S":"Al6101CAwh_NKR-gr67Xx/_N_T_/layout"},"path":{"S":"Al6101CAwh_NKR-gr67Xx/_global-error"},"revalidatedAt":{"N":"1"}},{"tag":{"S":"Al6101CAwh_NKR-gr67Xx/_N_T_/_global-error/layout"},"path":{"S":"Al6101CAwh_NKR-gr67Xx/_global-error"},"revalidatedAt":{"N":"1"}},{"tag":{"S":"Al6101CAwh_NKR-gr67Xx/_N_T_/_global-error/page"},"path":{"S":"Al6101CAwh_NKR-gr67Xx/_global-error"},"revalidatedAt":{"N":"1"}},{"tag":{"S":"Al6101CAwh_NKR-gr67Xx/_N_T_/_global-error"},"path":{"S":"Al6101CAwh_NKR-gr67Xx/_global-error"},"revalidatedAt":{"N":"1"}},{"tag":{"S":"Al6101CAwh_NKR-gr67Xx/_N_T_/layout"},"path":{"S":"Al6101CAwh_NKR-gr67Xx/_not-found"},"revalidatedAt":{"N":"1"}},{"tag":{"S":"Al6101CAwh_NKR-gr67Xx/_N_T_/_not-found/layout"},"path":{"S":"Al6101CAwh_NKR-gr67Xx/_not-found"},"revalidatedAt":{"N":"1"}},{"tag":{"S":"Al6101CAwh_NKR-gr67Xx/_N_T_/_not-found/page"},"path":{"S":"Al6101CAwh_NKR-gr67Xx/_not-found"},"revalidatedAt":{"N":"1"}},{"tag":{"S":"Al6101CAwh_NKR-gr67Xx/_N_T_/_not-found"},"path":{"S":"Al6101CAwh_NKR-gr67Xx/_not-found"},"revalidatedAt":{"N":"1"}}]